xiyou_sdk/__init__.py
xiyou_sdk/auth.py
xiyou_auth_sdk-1.0.0.dist-info/LICENSE
xiyou_auth_sdk-1.0.0.dist-info/METADATA
xiyou_auth_sdk-1.0.0.dist-info/WHEEL
xiyou_auth_sdk-1.0.0.dist-info/top_level.txt
xiyou_auth_sdk-1.0.0.dist-info/RECORD
